odoo/addons/energy_project_energy_communities/__init__.py
odoo/addons/energy_project_energy_communities/__manifest__.py
odoo/addons/energy_project_energy_communities/i18n/ca_ES.po
odoo/addons/energy_project_energy_communities/i18n/energy_project_energy_communities.pot
odoo/addons/energy_project_energy_communities/i18n/es.po
odoo/addons/energy_project_energy_communities/i18n/eu_ES.po
odoo/addons/energy_project_energy_communities/models/__init__.py
odoo/addons/energy_project_energy_communities/models/inscription.py
odoo/addons/energy_project_energy_communities/security/res_users_role_data.xml
odoo/addons/energy_project_energy_communities/static/description/icon.png
odoo14_addon_energy_project_energy_communities-14.0.1.3.0.dist-info/METADATA
odoo14_addon_energy_project_energy_communities-14.0.1.3.0.dist-info/WHEEL
odoo14_addon_energy_project_energy_communities-14.0.1.3.0.dist-info/top_level.txt
odoo14_addon_energy_project_energy_communities-14.0.1.3.0.dist-info/RECORD
